[{"countryCode":"ro","europarlID":"96823","attendance":"89","roleInGroup":"Member","displayName":"Petru Constantin Luhan","sortName":"Luhan, Petru Constantin ","Miniatur":"96823.jpg","AbgBild":"96823.jpg","mepid":"308","sex":"m","yearofbirth":"1977","group":"PPE","votes":[{"v_dbid":"5249","exists":true,"vote":0},{"v_dbid":"4462","exists":true,"vote":-1},{"v_dbid":"5216","exists":true,"vote":0},{"v_dbid":"5217","exists":true,"vote":0},{"v_dbid":"4662","exists":true,"vote":1},{"v_dbid":"44475227","exists":false,"vote":0},{"v_dbid":"5243","exists":true,"vote":0},{"v_dbid":"4458","exists":true,"vote":-1},{"v_dbid":"4657","exists":true,"vote":1},{"v_dbid":"4661","exists":true,"vote":1}]}]