[{"countryCode":"ro","europarlID":"33990","attendance":"86","roleInGroup":"Member","displayName":"Adrian Severin","sortName":"Severin, Adrian ","Miniatur":"33990.jpg","AbgBild":"33990.jpg","mepid":"704","sex":"m","yearofbirth":"1954","group":"NI","votes":[{"v_dbid":"5249","exists":true,"vote":1},{"v_dbid":"4462","exists":true,"vote":1},{"v_dbid":"5216","exists":true,"vote":-1},{"v_dbid":"5217","exists":true,"vote":1},{"v_dbid":"4662","exists":true,"vote":1},{"v_dbid":"4447","exists":true,"vote":1},{"v_dbid":"5227","exists":true,"vote":1},{"v_dbid":"5243","exists":true,"vote":1},{"v_dbid":"4458","exists":true,"vote":1},{"v_dbid":"4657","exists":true,"vote":1},{"v_dbid":"4661","exists":true,"vote":1}]}]