[{"countryCode":"es","europarlID":"24942","attendance":"0","roleInGroup":"","displayName":"Ana Miranda","sortName":"Miranda, Ana","Miniatur":"24942.jpg","AbgBild":"24942.jpg","mepid":"795","sex":"f","yearofbirth":"0","group":"VALE","votes":[{"v_dbid":"5249","exists":false,"vote":0},{"v_dbid":"4462","exists":true,"vote":1},{"v_dbid":"5216","exists":false,"vote":0},{"v_dbid":"5217","exists":false,"vote":0},{"v_dbid":"4662","exists":false,"vote":0},{"v_dbid":"4447","exists":true,"vote":1},{"v_dbid":"5227","exists":false,"vote":0},{"v_dbid":"5243","exists":false,"vote":0},{"v_dbid":"4458","exists":true,"vote":1},{"v_dbid":"4657","exists":false,"vote":0},{"v_dbid":"4661","exists":false,"vote":0}]}]