[{"countryCode":"bg","europarlID":"34249","attendance":"96","roleInGroup":"Member of the Bureau","displayName":"Filiz Hakaeva Hyusmenova","sortName":"Hyusmenova, Filiz Hakaeva ","Miniatur":"34249.jpg","AbgBild":"34249.jpg","mepid":"151","sex":"f","yearofbirth":"1966","group":"ALDE","votes":[{"v_dbid":"3485","exists":true,"vote":1},{"v_dbid":"3301","exists":true,"vote":1},{"v_dbid":"5327","exists":true,"vote":1},{"v_dbid":"2171","exists":true,"vote":1},{"v_dbid":"2691","exists":true,"vote":1},{"v_dbid":"5579","exists":true,"vote":1},{"v_dbid":"5297","exists":true,"vote":-1}]}]