[{"countryCode":"it","europarlID":"28370","attendance":"87","roleInGroup":"Member","displayName":"Vittorio Prodi","sortName":"Prodi, Vittorio ","Miniatur":"28370.jpg","AbgBild":"28370.jpg","mepid":"630","sex":"m","yearofbirth":"1937","group":"SD","votes":[{"v_dbid":"3485","exists":true,"vote":1},{"v_dbid":"3301","exists":true,"vote":1},{"v_dbid":"5327","exists":true,"vote":1},{"v_dbid":"2171","exists":true,"vote":1},{"v_dbid":"2691","exists":true,"vote":1},{"v_dbid":"5579","exists":true,"vote":1},{"v_dbid":"5297","exists":true,"vote":0}]}]