[{"countryCode":"de","europarlID":"96646","attendance":"96","roleInGroup":"Member","displayName":"Helmut Scholz","sortName":"Scholz, Helmut ","Miniatur":"96646.jpg","AbgBild":"96646.jpg","mepid":"455","sex":"m","yearofbirth":"1954","group":"GUENGL","votes":[{"v_dbid":"3358","exists":true,"vote":1},{"v_dbid":"3361","exists":true,"vote":-1},{"v_dbid":"4787","exists":true,"vote":1},{"v_dbid":"4788","exists":true,"vote":1},{"v_dbid":"4792","exists":true,"vote":1},{"v_dbid":"5689","exists":true,"vote":1},{"v_dbid":"5747","exists":true,"vote":1},{"v_dbid":"5748","exists":true,"vote":1}]}]