[{"countryCode":"cz","europarlID":"23712","attendance":"72","roleInGroup":"Chair","displayName":"Jan Zahradil","sortName":"Zahradil, Jan ","Miniatur":"23712.jpg","AbgBild":"23712.jpg","mepid":"435","sex":"m","yearofbirth":"1963","group":"ECR","votes":[{"v_dbid":"3358","exists":true,"vote":-1},{"v_dbid":"3361","exists":true,"vote":-1},{"v_dbid":"4787","exists":true,"vote":0},{"v_dbid":"4788","exists":true,"vote":0},{"v_dbid":"4792","exists":true,"vote":0},{"v_dbid":"5689","exists":true,"vote":0},{"v_dbid":"5747","exists":true,"vote":0},{"v_dbid":"5748","exists":true,"vote":0}]}]