[{"countryCode":"gb","europarlID":"28132","attendance":"95","roleInGroup":"Member","displayName":"Richard Ashworth","sortName":"Ashworth, Richard ","Miniatur":"28132.jpg","AbgBild":"28132.jpg","mepid":"182","sex":"m","yearofbirth":"1947","group":"ECR","votes":[{"v_dbid":"4995","exists":true,"vote":1},{"v_dbid":"5004","exists":true,"vote":-1},{"v_dbid":"5276","exists":true,"vote":-1},{"v_dbid":"4096","exists":true,"vote":-1},{"v_dbid":"3939","exists":true,"vote":-1},{"v_dbid":"3708","exists":true,"vote":0},{"v_dbid":"3082","exists":true,"vote":1},{"v_dbid":"2636","exists":true,"vote":-1},{"v_dbid":"2340","exists":true,"vote":-1},{"v_dbid":"2189","exists":true,"vote":-1},{"v_dbid":"220","exists":true,"vote":1}]}]