[{"countryCode":"fr","europarlID":"96849","attendance":"92","roleInGroup":"Member","displayName":"Alain Cadec","sortName":"Cadec, Alain ","Miniatur":"96849.jpg","AbgBild":"96849.jpg","mepid":"233","sex":"m","yearofbirth":"1953","group":"PPE","votes":[{"v_dbid":"4995","exists":true,"vote":1},{"v_dbid":"5004","exists":true,"vote":-1},{"v_dbid":"5276","exists":true,"vote":1},{"v_dbid":"4096","exists":true,"vote":-1},{"v_dbid":"3939","exists":true,"vote":-1},{"v_dbid":"3708","exists":true,"vote":1},{"v_dbid":"3082","exists":true,"vote":1},{"v_dbid":"2636","exists":true,"vote":0},{"v_dbid":"2340","exists":true,"vote":-1},{"v_dbid":"2189","exists":true,"vote":1},{"v_dbid":"220","exists":true,"vote":1}]}]