[{"countryCode":"fi","europarlID":"96682","attendance":"89","roleInGroup":"Member","displayName":"Sari Essayah","sortName":"Essayah, Sari ","Miniatur":"96682.jpg","AbgBild":"96682.jpg","mepid":"474","sex":"f","yearofbirth":"1967","group":"PPE","votes":[{"v_dbid":"4995","exists":true,"vote":1},{"v_dbid":"5004","exists":true,"vote":-1},{"v_dbid":"5276","exists":true,"vote":-1},{"v_dbid":"4096","exists":true,"vote":-1},{"v_dbid":"3939","exists":true,"vote":-1},{"v_dbid":"3708","exists":true,"vote":1},{"v_dbid":"3082","exists":true,"vote":1},{"v_dbid":"2636","exists":true,"vote":-1},{"v_dbid":"2340","exists":true,"vote":-1},{"v_dbid":"2189","exists":true,"vote":1},{"v_dbid":"220","exists":true,"vote":1}]}]