[{"countryCode":"be","europarlID":"5729","attendance":"91","roleInGroup":"Member","displayName":"Kathleen Van Brempt","sortName":"Van Brempt, Kathleen ","Miniatur":"5729.jpg","AbgBild":"5729.jpg","mepid":"95","sex":"f","yearofbirth":"1969","group":"SD","votes":[{"v_dbid":"4995","exists":true,"vote":-1},{"v_dbid":"5004","exists":true,"vote":1},{"v_dbid":"5276","exists":true,"vote":1},{"v_dbid":"4096","exists":true,"vote":1},{"v_dbid":"3939","exists":true,"vote":1},{"v_dbid":"3708","exists":true,"vote":1},{"v_dbid":"3082","exists":true,"vote":1},{"v_dbid":"2636","exists":true,"vote":1},{"v_dbid":"2340","exists":true,"vote":0},{"v_dbid":"2189","exists":true,"vote":1},{"v_dbid":"220","exists":true,"vote":1}]}]