[{"countryCode":"pl","europarlID":"96778","attendance":"90","roleInGroup":"Member","displayName":"Artur Zasada","sortName":"Zasada, Artur ","Miniatur":"96778.jpg","AbgBild":"96778.jpg","mepid":"376","sex":"m","yearofbirth":"1969","group":"PPE","votes":[{"v_dbid":"3358","exists":true,"vote":-1},{"v_dbid":"3361","exists":true,"vote":1},{"v_dbid":"4787","exists":true,"vote":1},{"v_dbid":"4788","exists":true,"vote":-1},{"v_dbid":"4792","exists":true,"vote":-1},{"v_dbid":"5689","exists":true,"vote":-1},{"v_dbid":"5747","exists":true,"vote":-1},{"v_dbid":"5748","exists":true,"vote":-1}]}]